{"desc": "Website Owner's Manual helps you form a vision for your site, guides you through the process of selecting a web design agency, and gives you enough background information to make intelligent decisions throughout the development process. This book provides a jargon-free overview of web design, including accessibility, usability, online marketing, and web development techniques. You'll gain a practical understanding of the technologies, processes, and ideas that drive a successful website.", "title": "Website Owner's Manual", "thumbnailUrl": "https://s3.amazonaws.com/AKIAJC5RLADLUMVRPFDQ.book-thumb-images/boag.jpg", "authors": ["Paul A. Boag"], "categories": ["Internet"]}